midomtoolbox/__init__.py
midomtoolbox/render.py
midomtoolbox/ctp/__init__.py
midomtoolbox/ctp/config_script.py
midomtoolbox/ctp/context.py
midomtoolbox/ctp/elements.py
midomtoolbox/ctp/exceptions.py
midomtoolbox/ctp/parser.py
midomtoolbox/ctp/pipeline.py
midomtoolbox/ctp/tagdictionary.py
midomtoolbox/ctp/translation.py
midomtoolbox/templates/__init__.py
midomtoolbox/templates/private_tags_table.md.j2
midomtoolbox/templates/protocol.md.j2
midomtoolbox/templates/tags_table.md.j2
midomtoolbox-0.2.0.dist-info/licenses/LICENSE
midomtoolbox-0.2.0.dist-info/METADATA
midomtoolbox-0.2.0.dist-info/WHEEL
midomtoolbox-0.2.0.dist-info/top_level.txt
midomtoolbox-0.2.0.dist-info/RECORD
