Metadata-Version: 2.4
Name: midomtoolbox
Version: 0.2.0
Summary: Shape, convert, summarize and analyse MIDOM deidentification Protocols
License-Expression: Apache-2.0
Classifier: Development Status :: 4 - Beta
Classifier: Intended Audience :: Developers
Classifier: Topic :: Scientific/Engineering :: Medical Science Apps.
Classifier: Programming Language :: Python :: 3.12
Classifier: Programming Language :: Python :: 3.13
Requires-Python: >=3.12
License-File: LICENSE
Requires-Dist: jinja2>=3.1.6
Requires-Dist: lark>=1.2.2
Requires-Dist: midom>=0.3.1
Requires-Dist: pre-commit>=4.3.0
Requires-Dist: pydicom>=3.0.1
Requires-Dist: pytest-cov>=7.0.0
Requires-Dist: tabulate>=0.9.0
Dynamic: license-file
